p_elasticsearch_easy/__init__.py
p_elasticsearch_easy/elasticsearch_base.py
p_elasticsearch_easy/elasticsearch_dsl.py
p_elasticsearch_easy/elasticsearch_native.py
p_elasticsearch_easy/constants/__init__.py
p_elasticsearch_easy/constants/constants.py
p_elasticsearch_easy/exceptions/__init__.py
p_elasticsearch_easy/exceptions/custom_exceptions.py
p_elasticsearch_easy/exceptions/elasticsearch_exception.py
p_elasticsearch_easy-1.1.1.dist-info/LICENSE
p_elasticsearch_easy-1.1.1.dist-info/METADATA
p_elasticsearch_easy-1.1.1.dist-info/WHEEL
p_elasticsearch_easy-1.1.1.dist-info/top_level.txt
p_elasticsearch_easy-1.1.1.dist-info/RECORD
