Metadata-Version: 2.1
Name: p_elasticsearch_easy
Version: 1.1.1
Summary: A base resource for working with the Elasticsearch and ElasticsearchDSL libraries in a simple way.
Author-email: Adrián Pérez <apo00015@red.ujaen.es>
License: GPL-3.0-or-later
Project-URL: Homepage, https://github.com/apo00015
Project-URL: Repository, https://github.com/apo00015/P_Elascticsearch_Easy
Project-URL: Issue Tracker, https://github.com/apo00015/P_Elascticsearch_Easy/issues
Classifier: Development Status :: 5 - Production/Stable
Classifier: Intended Audience :: Developers
Classifier: License :: OSI Approved :: GNU General Public License v3 or later (GPLv3+)
Classifier: Programming Language :: Python :: 3
Classifier: Programming Language :: Python :: 3.8
Classifier: Programming Language :: Python :: 3.9
Classifier: Programming Language :: Python :: 3.10
Classifier: Operating System :: OS Independent
Classifier: Topic :: Software Development :: Libraries :: Python Modules
Classifier: Topic :: Database
Requires-Python: >=3.8
License-File: LICENSE
Requires-Dist: elasticsearch <9.0,>=8.11
Requires-Dist: elasticsearch-dsl <9.0,>=8.11
Provides-Extra: dev
Requires-Dist: pytest ; extra == 'dev'
Requires-Dist: pytest-cov ; extra == 'dev'
